Testing/FSM/FSM_new.v
module afc_fsm_6bit (
    input wire clk,
    input wire rst_n,
    input wire [2:0] comp_in,    // FAST=3'b100, SLOW=3'b010, FREEZE=3'b001
    output reg [5:0] state_out   // [5]=finish, [4:0]=band(0-31)
);

    localparam FREEZE = 3'b001, SLOW = 3'b010, FAST = 3'b100;
    localparam IDLE_BAND = 5'd16;

    reg [4:0] low, high, mid;
    reg finish;
    reg [4:0] band;

    // Initialization and band update logic
    always @(posedge clk or negedge rst_n) begin
        if (!rst_n) begin
            low    <= 5'd0;
            high   <= 5'd31;
            mid    <= IDLE_BAND;
            band   <= IDLE_BAND;
            finish <= 1'b0;
        end else if (!finish) begin
            case (comp_in)
                FREEZE: begin
                    finish <= 1'b1;
                    band   <= mid;
                end
                SLOW: begin
                    low  <= mid + 1;
                    high <= high;
                    mid  <= ((mid + 1) + high) >> 1;
                    band <= ((mid + 1) + high) >> 1;
                end
                FAST: begin
                    low  <= low;
                    high <= mid - 1;
                    mid  <= (low + (mid - 1)) >> 1;
                    band <= (low + (mid - 1)) >> 1;
                end
                default: ; // Hold state
            endcase
        end
        // If finish, hold values
    end

    // Output assignment
    always @(*) begin
        state_out = {finish, band};
    end

endmodule

Testing/FSM/FSM_new_tb.v
`timescale 1ns/1ps

module afc_fsm_tb;
    // Parameters
    parameter CLK_PERIOD = 10;  // 10ns clock period (100MHz)
    
    // Testbench signals
    reg clk;
    reg rst_n;
    reg [2:0] comp_in;
    wire [5:0] state_out;
    
    // Instantiate the DUT (Device Under Test)
    afc_fsm_6bit dut (
        .clk(clk),
        .rst_n(rst_n),
        .comp_in(comp_in),
        .state_out(state_out)
    );
    
    // Clock generation
    initial begin
        clk = 0;
        forever #(CLK_PERIOD/2) clk = ~clk;
    end
    
    // Testbench stimulus and monitoring
    initial begin
        // Initialize
        rst_n = 0;
        comp_in = 3'b000;
        
        // Apply initial reset
        #(CLK_PERIOD*2);
        rst_n = 1;
        #(CLK_PERIOD*2);
        
        // Test Case 1: IDLE -> S1100 (Slow from IDLE)
        $display("Test Case 1: IDLE -> S1100 (Slow)");
        comp_in = 3'b010; // Slow
        #(CLK_PERIOD);
        $display("State: %b (Expected: 01100)", state_out);
        
        // Test Case 2: S1100 -> S1101 (Slow again)
        $display("Test Case 2: S1100 -> S1101 (Slow)");
        comp_in = 3'b010; // Slow
        #(CLK_PERIOD);
        $display("State: %b (Expected: 01101)", state_out);
        
        // Test Case 3: S1101 -> F1101 (Freeze)
        $display("Test Case 3: S1101 -> F1101 (Freeze)");
        comp_in = 3'b001; // Freeze
        #(CLK_PERIOD);
        $display("State: %b (Expected: 11101)", state_out);
        
        // Test Case 4: F1101 should remain in finished state
        $display("Test Case 4: F1101 should remain in finished state");
        comp_in = 3'b010; // Try Slow (should have no effect)
        #(CLK_PERIOD);
        $display("State: %b (Expected: 11101)", state_out);
        
        // Reset to start new test sequence
        rst_n = 0;
        #(CLK_PERIOD*2);
        rst_n = 1;
        #(CLK_PERIOD*2);
        
        // End simulation
        #(CLK_PERIOD*5);
        $display("Testbench completed");
        $finish;
    end
    
    // Optional: Add waveform dumping for visualization
    initial begin
        $dumpfile("afc_fsm.vcd");
        $dumpvars(0, afc_fsm_tb);
    end
endmodule

Testing/FSM/afc_fsm.vcd
$date
	Wed May 14 08:06:02 2025
$end
$version
	Icarus Verilog
$end
$timescale
	1ps
$end
$scope module afc_fsm_tb $end
$var wire 6 ! state_out [5:0] $end
$var parameter 32 " CLK_PERIOD $end
$var reg 1 # clk $end
$var reg 3 $ comp_in [2:0] $end
$var reg 1 % rst_n $end
$scope module dut $end
$var wire 1 # clk $end
$var wire 3 & comp_in [2:0] $end
$var wire 1 % rst_n $end
$var parameter 3 ' FAST $end
$var parameter 3 ( FREEZE $end
$var parameter 5 ) IDLE_BAND $end
$var parameter 3 * SLOW $end
$var reg 5 + band [4:0] $end
$var reg 1 , finish $end
$var reg 5 - high [4:0] $end
$var reg 5 . low [4:0] $end
$var reg 5 / mid [4:0] $end
$var reg 6 0 state_out [5:0] $end
$upscope $end
$upscope $end
$enddefinitions $end
$comment Show the parameter values. $end
$dumpall
b10 *
b10000 )
b1 (
b100 '
b1010 "
$end
#0
$dumpvars
b10000 0
b10000 /
b0 .
b11111 -
0,
b10000 +
b0 &
0%
b0 $
0#
b10000 !
$end
#5000
1#
#10000
0#
#15000
1#
#20000
0#
1%
#25000
1#
#30000
0#
#35000
1#
#40000
0#
b10 $
b10 &
#45000
b11000 !
b11000 0
b11000 +
b11000 /
b10001 .
1#
#50000
0#
#55000
b11100 !
b11100 0
b11100 +
b11100 /
b11001 .
1#
#60000
0#
b1 $
b1 &
#65000
b111100 !
b111100 0
1,
1#
#70000
0#
b10 $
b10 &
#75000
1#
#80000
b10000 !
b10000 0
0,
b10000 +
b10000 /
b0 .
0#
0%
#85000
1#
#90000
0#
#95000
1#
#100000
0#
1%
#105000
b11000 !
b11000 0
b11000 +
b11000 /
b10001 .
1#
#110000
0#
#115000
b11100 !
b11100 0
b11100 +
b11100 /
b11001 .
1#
#120000
0#
#125000
b11110 !
b11110 0
b11110 +
b11110 /
b11101 .
1#
#130000
0#
#135000
b11111 !
b11111 0
b11111 +
b11111 /
b11111 .
1#
#140000
0#
#145000
b0 .
1#
